{"nombre_cliente": "Juvencio Alarcón Amador", "dni_cliente": "25494387Z", "calle_cliente": "Calle del Urola", "cp_cliente": "24411", "población_cliente": "Ponferrada", "provincia_cliente": "León", "nombre_comercializadora": "ELECTRICA CALLOSINA, S.L.", "cif_comercializadora": "B53480547", "dirección_comercializadora": "C/ RAMBLA ALTA, Nº7", "cp_comercializadora": "03360", "población_comercializadora": "CALLOSA DE SEGURA", "provincia_comercializadora": "Alicante", "número_factura": "BV1209728205", "inicio_periodo": "05.04.2021", "fin_periodo": "05.05.2021", "importe_factura": "135,01", "fecha_cargo": "10.05.2021", "consumo_periodo": 449, "potencia_contratada": "6,472"}