{"nombre_cliente": "JOHANNA DEL CASTILLO LARIOS", "dni_cliente": "91538504E", "calle_cliente": "Plaza de Santa Paula Montal", "cp_cliente": "28004", "población_cliente": "Madrid", "provincia_cliente": "Madrid", "nombre_comercializadora": "COMERCIALIZACION ELECTRICA CATALANA SL", "cif_comercializadora": "B65960551", "dirección_comercializadora": "C/ INDUSTRIA, 137", "cp_comercializadora": "08025", "población_comercializadora": "BARCELONA", "provincia_comercializadora": "Barcelona", "número_factura": "M4923956166", "inicio_periodo": "17.01.2006", "fin_periodo": "18.03.2006", "importe_factura": "28,28", "fecha_cargo": "23.03.2006", "consumo_periodo": 0, "potencia_contratada": "3,560"}