{"nombre_cliente": "SÓCRATES PERAZA NAVARRO", "dni_cliente": "95006636F", "calle_cliente": "Calle de Italia", "cp_cliente": "06458", "población_cliente": "Valle de la Serena", "provincia_cliente": "Badajoz", "nombre_comercializadora": "INNOVA DESARROLLO Y EFICIENCIA ENERGÉTICA, S.L.", "cif_comercializadora": "B24698359", "dirección_comercializadora": "C/ ALCALDE ANTONIO RAMOS, 8 3ºA NAVATEJERA", "cp_comercializadora": "24193", "población_comercializadora": "VILLAQUILAMBRE", "provincia_comercializadora": "León", "número_factura": "BX9146180207", "inicio_periodo": "08.07.2003", "fin_periodo": "07.08.2003", "importe_factura": "190,29", "fecha_cargo": "12.08.2003", "consumo_periodo": 545, "potencia_contratada": "4,814"}