{"nombre_cliente": "Laia Zabaleta Travieso", "dni_cliente": "53517917E", "calle_cliente": "Via Galiana", "cp_cliente": "16647", "población_cliente": "Villaescusa de Haro", "provincia_cliente": "Cuenca", "nombre_comercializadora": "AAYUM COMPANYIA CATALANA SUBMINISTRADORA D'ENERGIA S.L", "cif_comercializadora": "B65509887", "dirección_comercializadora": "AVENIDA PAÍSOS CATALANS NÚM 29-LOCAL 1", "cp_comercializadora": "08500", "población_comercializadora": "VIC", "provincia_comercializadora": "Barcelona", "número_factura": "QP6197479377", "inicio_periodo": "26.05.2015", "fin_periodo": "25.07.2015", "importe_factura": "433,66", "fecha_cargo": "30.07.2015", "consumo_periodo": 1416, "potencia_contratada": "2,868"}