{"nombre_cliente": "EMERSON TRONCOSO AGUSTÍN", "dni_cliente": "89751691X", "calle_cliente": "Calle de las Costaneras", "cp_cliente": "34889", "población_cliente": "Velilla del Río Carrión", "provincia_cliente": "Palencia", "nombre_comercializadora": "COOP VALENCIANA ELECTRODISTRIBUIDORA DE FUERZA Y ALUMBRADO SERRALLO", "cif_comercializadora": "F12057196", "dirección_comercializadora": "CAMINO ALMALAFA, 375", "cp_comercializadora": "12100", "población_comercializadora": "GRAO DE CASTELLÓN", "provincia_comercializadora": "Castellón", "número_factura": "V2688379188", "inicio_periodo": "20.11.2000", "fin_periodo": "19.01.2001", "importe_factura": "198,30", "fecha_cargo": "24.01.2001", "consumo_periodo": 744, "potencia_contratada": "2,555"}