{"nombre_cliente": "Pantaleón Redondo Sol", "dni_cliente": "86440784E", "calle_cliente": "Camino Finca Cerro de la Mina", "cp_cliente": "38739", "población_cliente": "Villa de Mazo", "provincia_cliente": "Santa Cruz de Tenerife", "nombre_comercializadora": "INGENIERÍA Y COMERCIALIZACIÓN DEL GAS S.A", "cif_comercializadora": "A73137788", "dirección_comercializadora": "C/ RUIZ ZORRILLA Nº2 PISO 3", "cp_comercializadora": "12001", "población_comercializadora": "CASTELLÓN", "provincia_comercializadora": "Castellón", "número_factura": "SO4089250079", "inicio_periodo": "09.02.2001", "fin_periodo": "10.04.2001", "importe_factura": "34,34", "fecha_cargo": "15.04.2001", "consumo_periodo": 0, "potencia_contratada": "4,314"}