{"nombre_cliente": "Carlomagno Cuéllar Enríquez", "dni_cliente": "11833586V", "calle_cliente": "Calle de Emilio Bellvis", "cp_cliente": "10748", "población_cliente": "Abadía", "provincia_cliente": "Cáceres", "nombre_comercializadora": "EKILUZ ENERGÍA COMERCIALIZADORA, S.L.", "cif_comercializadora": "B75229369", "dirección_comercializadora": "C/ DEL HIERRO Nº 33 (planta 3, nave 7)", "cp_comercializadora": "28045", "población_comercializadora": "Madrid", "provincia_comercializadora": "MADRID", "número_factura": "O1778034497", "inicio_periodo": "09.09.1993", "fin_periodo": "08.11.1993", "importe_factura": "47,83", "fecha_cargo": "13.11.1993", "consumo_periodo": 40, "potencia_contratada": "4,829"}