{"nombre_cliente": "KENDRA RAMÍREZ RAMÓN", "dni_cliente": "16260925V", "calle_cliente": "Avenida de la Paloma", "cp_cliente": "34259", "población_cliente": "Cordovilla la Real", "provincia_cliente": "Palencia", "nombre_comercializadora": "REPSOL COMERCIALIZADORA DE ELECTRICIDAD Y GAS, S.L.U", "cif_comercializadora": "B39540760", "dirección_comercializadora": "C/ ISABEL TORRES, Nº 19", "cp_comercializadora": "39011", "población_comercializadora": "SANTANDER", "provincia_comercializadora": "Cantabria", "número_factura": "Z5231002650", "inicio_periodo": "09.05.2016", "fin_periodo": "08.07.2016", "importe_factura": "144,31", "fecha_cargo": "13.07.2016", "consumo_periodo": 426, "potencia_contratada": "5,558"}