{"nombre_cliente": "IZASKUM SALA VARGAS", "dni_cliente": "11047069P", "calle_cliente": "Calle el Cristo", "cp_cliente": "34111", "población_cliente": "Villaluenga de la Vega", "provincia_cliente": "Palencia", "nombre_comercializadora": "DREUE ELECTRIC, S.L.U", "cif_comercializadora": "B98202237", "dirección_comercializadora": "C/ THOMAS ALVA EDISON, 7 - PARQUE TECNOLÓGICO DE VALENCIA", "cp_comercializadora": "46980", "población_comercializadora": "PATERNA", "provincia_comercializadora": "Valencia", "número_factura": "J9146263567", "inicio_periodo": "17.06.2015", "fin_periodo": "16.08.2015", "importe_factura": "169,14", "fecha_cargo": "21.08.2015", "consumo_periodo": 494, "potencia_contratada": "3,635"}