{"nombre_cliente": "Salvino Sandino Valenzuela", "dni_cliente": "15972179J", "calle_cliente": "Plaza del Portillo Romero", "cp_cliente": "17200", "población_cliente": "Palafrugell", "provincia_cliente": "Girona", "nombre_comercializadora": "COMERCIALIZADORA EUROPEA DE ENERGIA LIMPIA, S.L.", "cif_comercializadora": "B76361393", "dirección_comercializadora": "C/ RUPERTO NEGRÍN 4, OFICINA 1", "cp_comercializadora": "35500", "población_comercializadora": "ARRECIFE", "provincia_comercializadora": "PALMAS, LAS", "número_factura": "BH3852522370", "inicio_periodo": "26.07.2018", "fin_periodo": "25.08.2018", "importe_factura": "194,85", "fecha_cargo": "30.08.2018", "consumo_periodo": 602, "potencia_contratada": "5,536"}