{"nombre_cliente": "ANUNCIATA ALTAMIRANO HERNÁNDEZ", "dni_cliente": "61706200Y", "calle_cliente": "Calle Tahona", "cp_cliente": "01520", "población_cliente": "Arratzua-Ubarrundia", "provincia_cliente": "Araba/Álava", "nombre_comercializadora": "URANOSCOPIDAE II ENERGIA, S.L.", "cif_comercializadora": "B88628581", "dirección_comercializadora": "MARQUES DE LA AHUMADA, 5", "cp_comercializadora": "28028", "población_comercializadora": "MADRID", "provincia_comercializadora": "MADRID", "número_factura": "B9984920350", "inicio_periodo": "14.07.2001", "fin_periodo": "13.08.2001", "importe_factura": "82,99", "fecha_cargo": "18.08.2001", "consumo_periodo": 206, "potencia_contratada": "5,670"}