{"nombre_cliente": "PAULO ROMÁN OSPINO", "dni_cliente": "71096583H", "calle_cliente": "Calle del Río Sar", "cp_cliente": "10829", "población_cliente": "Riolobos", "provincia_cliente": "Cáceres", "nombre_comercializadora": "OLIVIA COMERCIALIZADORA S.L.U.", "cif_comercializadora": "B72352503", "dirección_comercializadora": "VIA IRLANDA SN", "cp_comercializadora": "11012", "población_comercializadora": "CÁDIZ", "provincia_comercializadora": "CÁDIZ", "número_factura": "VS5157961546", "inicio_periodo": "31.01.2001", "fin_periodo": "01.04.2001", "importe_factura": "404,79", "fecha_cargo": "06.04.2001", "consumo_periodo": 1134, "potencia_contratada": "1,945"}