{"nombre_cliente": "KAY MATÍAS ROBLES", "dni_cliente": "51279403Y", "calle_cliente": "Calle Bristol", "cp_cliente": "45138", "población_cliente": "Los Navalucillos", "provincia_cliente": "Toledo", "nombre_comercializadora": "ELECTRICA DE GUADASSUAR COOP V", "cif_comercializadora": "F46004750", "dirección_comercializadora": "GRAN VIA, 88", "cp_comercializadora": "46610", "población_comercializadora": "GUADASSUAR", "provincia_comercializadora": "Valencia", "número_factura": "H9899337545", "inicio_periodo": "27.01.2007", "fin_periodo": "28.03.2007", "importe_factura": "174,54", "fecha_cargo": "02.04.2007", "consumo_periodo": 742, "potencia_contratada": "2,955"}