{"nombre_cliente": "Rosalía Rovira Perdomo", "dni_cliente": "71437782N", "calle_cliente": "Calle del Camino Sur", "cp_cliente": "03690", "población_cliente": "San Vicente del Raspeig/Sant Vicent del Raspeig", "provincia_cliente": "Alicante/Alacant", "nombre_comercializadora": "ELEK COMERCIALIZADORA ELECTRICA S.L.", "cif_comercializadora": "B98825680", "dirección_comercializadora": "AVDA. CORTES VALENCIANAS, 58 9º OF.1 Ed. SOROLLA CENTER", "cp_comercializadora": "46015", "población_comercializadora": "VALENCIA", "provincia_comercializadora": "Valencia", "número_factura": "ST1818305417", "inicio_periodo": "22.11.2021", "fin_periodo": "21.01.2022", "importe_factura": "182,82", "fecha_cargo": "26.01.2022", "consumo_periodo": 496, "potencia_contratada": "4,328"}